{
  "unversionedId": "Guide_de_l_administrateur/Présentation_du_produit/Les_ports",
  "id": "Guide_de_l_administrateur/Présentation_du_produit/Les_ports",
  "title": "Les ports",
  "description": "| Nécessité | Numéro de port | TLS/SSL/PLAIN | Description |",
  "source": "@site/docs/Guide_de_l_administrateur/Présentation_du_produit/Les_ports.md",
  "sourceDirName": "Guide_de_l_administrateur/Présentation_du_produit",
  "slug": "/Guide_de_l_administrateur/Présentation_du_produit/Les_ports",
  "permalink": "/docs/Guide_de_l_administrateur/Présentation_du_produit/Les_ports",
  "tags": [],
  "version": "current",
  "frontMatter": {
    "title": "Les ports",
    "confluence_id": 57771265,
    "position": 50
  },
  "sidebar": "bmdocs",
  "previous": {
    "title": "Applications et composants",
    "permalink": "/docs/Guide_de_l_administrateur/Présentation_du_produit/Applications_et_composants"
  },
  "next": {
    "title": "Les services",
    "permalink": "/docs/Guide_de_l_administrateur/Présentation_du_produit/Les_services"
  }
}