{
  "unversionedId": "Restaurer les messages supprimes par un utilisateur",
  "id": "Restaurer les messages supprimes par un utilisateur",
  "title": "Restaurer les messages supprimes par un utilisateur",
  "description": "À partir de BlueMind 4.4, la corbeille est dite \"à double fond\" : elle propose un délai côté serveur pendant lequel les emails effacés sont conservés. Ainsi pendant ce délai une récupération peut être effectuée par l'utilisateur directement depuis son client Oulook (connecté en mapi) ou par l'administrateur depuis le serveur en ligne de commande.",
  "source": "@site/docs/Restaurer les messages supprimes par un utilisateur.md",
  "sourceDirName": ".",
  "slug": "/Restaurer les messages supprimes par un utilisateur",
  "permalink": "/docs/Restaurer les messages supprimes par un utilisateur",
  "editUrl": "https://github.com/facebook/docusaurus/tree/main/packages/create-docusaurus/templates/shared/docs/Restaurer les messages supprimes par un utilisateur.md",
  "tags": [],
  "version": "current",
  "frontMatter": {},
  "sidebar": "tutorialSidebar",
  "previous": {
    "title": "Restaurer l'agenda d'un utilisateur",
    "permalink": "/docs/Restaurer l'agenda d'un utilisateur"
  },
  "next": {
    "title": "Retrouver les carnets de domaine dans Outlook",
    "permalink": "/docs/Retrouver les carnets de domaine dans Outlook"
  }
}