{
  "unversionedId": "Archivage",
  "id": "Archivage",
  "title": "Archivage",
  "description": "BlueMind intègre un système d'archivage centralisé. Celui-ci permet de décharger les serveurs de stockage en stockant une partie des messages sur un point de montage différent dont les coûts de stockage sont inférieurs.",
  "source": "@site/docs/Archivage.md",
  "sourceDirName": ".",
  "slug": "/Archivage",
  "permalink": "/docs/Archivage",
  "editUrl": "https://github.com/facebook/docusaurus/tree/main/packages/create-docusaurus/templates/shared/docs/Archivage.md",
  "tags": [],
  "version": "current",
  "frontMatter": {},
  "sidebar": "tutorialSidebar",
  "previous": {
    "title": "Applications et Composants",
    "permalink": "/docs/Applications_et_Composants"
  },
  "next": {
    "title": "Authentification",
    "permalink": "/docs/Authentification"
  }
}